helga_notify.py
helga_notify-0.1.0.dist-info/DESCRIPTION.rst
helga_notify-0.1.0.dist-info/METADATA
helga_notify-0.1.0.dist-info/RECORD
helga_notify-0.1.0.dist-info/WHEEL
helga_notify-0.1.0.dist-info/entry_points.txt
helga_notify-0.1.0.dist-info/metadata.json
helga_notify-0.1.0.dist-info/top_level.txt
helga_notify-0.1.0.dist-info/zip-safe
