Metadata-Version: 2.0
Name: helga-notify
Version: 0.1.0
Summary: Companion to the announce webhook, this plugin is for notifying individual users/nicks
Home-page: UNKNOWN
Author: Mike Attwood
Author-email: mike@cybersponse.com
License: LICENSE
Keywords: irc bot notify helga
Platform: UNKNOWN
Classifier: Development Status :: 4 - Beta
Classifier: Environment :: Plugins
Classifier: Intended Audience :: Developers
Classifier: License :: OSI Approved :: GNU General Public License v3 (GPLv3)
Classifier: Operating System :: OS Independent
Classifier: Programming Language :: Python
Classifier: Topic :: Software Development :: Libraries :: Python Modules
